{"stats":{"minecraft:custom":{"minecraft:time_since_rest":8268,"minecraft:open_chest":12,"minecraft:crouch_one_cm":871,"minecraft:play_time":8268,"minecraft:sprint_one_cm":13111,"minecraft:damage_taken":190,"minecraft:walk_one_cm":7726,"minecraft:sneak_time":406,"minecraft:drop":4,"minecraft:jump":69,"minecraft:leave_game":2,"minecraft:time_since_death":8268,"minecraft:climb_one_cm":165,"minecraft:total_world_time":8268,"minecraft:fall_one_cm":39967,"minecraft:fly_one_cm":16135},"minecraft:mined":{"minecraft:vine":3,"colouredstuff:log_green":12,"colouredstuff:leaves_green":1},"minecraft:picked_up":{"colouredstuff:log_green":12,"colouredstuff:sapling_green":1,"mysticalagriculture:none_crop_essence":1,"minecraft:brown_dye":1,"sf5_things:brown_apple":1,"minecraft:green_dye":2},"minecraft:dropped":{"minecraft:brown_dye":1,"sf5_things:brown_apple":1,"minecraft:green_dye":2},"minecraft:used":{"colouredstuff:log_green":3,"colouredstuff:sapling_white":1,"sf5_things:brown_apple":1}},"DataVersion":3465}